{
  "format": "page",
  "id": "tabb",
  "label": "Tabb",
  "repeatable": false,
  "status": true,
  "json": {
    "Main": {
      "uid": {
        "type": "UID",
        "config": {
          "label": "uid",
          "placeholder": ""
        }
      },
      "slices": {
        "type": "Slices",
        "fieldset": "Slice Zone",
        "config": {
          "choices": {
            "breadcrumbs": {
              "type": "SharedSlice"
            },
            "compact_hero": {
              "type": "SharedSlice"
            },
            "contact": {
              "type": "SharedSlice"
            },
            "navigation_menu": {
              "type": "SharedSlice"
            },
            "Faq": {
              "type": "SharedSlice"
            },
            "ProjectShowcase": {
              "type": "SharedSlice"
            },
            "Process": {
              "type": "SharedSlice"
            },
            "Imageandtext": {
              "type": "SharedSlice"
            },
            "Expertiseareas": {
              "type": "SharedSlice"
            },
            "ServiceGrid": {
              "type": "SharedSlice"
            },
            "hero": {
              "type": "SharedSlice"
            },
            "privacy_text_box": {
              "type": "SharedSlice"
            }
          }
        }
      }
    },
    "SEO & Metadata": {
      "meta_title": {
        "config": {
          "label": "Meta Title",
          "placeholder": "A title of the page used for social media and search engines"
        },
        "type": "Text"
      },
      "meta_description": {
        "config": {
          "label": "Meta Description",
          "placeholder": "A brief summary of the page"
        },
        "type": "Text"
      },
      "meta_image": {
        "config": {
          "label": "Meta Image",
          "constraint": {
            "height": 630,
            "width": 1200
          },
          "thumbnails": []
        },
        "type": "Image"
      },
      "meta_image_alt_text": {
        "type": "Text",
        "config": {
          "label": "Meta Image Alt Text",
          "placeholder": ""
        }
      },
      "meta_keywords": {
        "type": "Group",
        "config": {
          "label": "Meta Keywords",
          "repeat": true,
          "fields": {
            "meta_keywords_text": {
              "type": "Text",
              "config": {
                "label": "Meta Keywords Text",
                "placeholder": ""
              }
            }
          }
        }
      },
      "meta_url": {
        "type": "Text",
        "config": {
          "label": "Meta URL",
          "placeholder": ""
        }
      }
    }
  }
}
